relax_xai/__init__.py
relax_xai/masking_functions.py
relax_xai/relax.py
relax_xai/utils.py
relax_xai-0.0.5.dist-info/LICENSE
relax_xai-0.0.5.dist-info/METADATA
relax_xai-0.0.5.dist-info/WHEEL
relax_xai-0.0.5.dist-info/top_level.txt
relax_xai-0.0.5.dist-info/RECORD
